{
	"frames": [
		{
			"filename": "bossLow.png",
			"position": {
				"x": 1,
				"y": 1,
				"w": 511,
				"h": 721
			},
			"rotated": false,
			"trimmed": false,
			"spriteSourceSize": {
				"x": 0,
				"y": 0,
				"w": 511,
				"h": 721
			},
			"sourceSize": {
				"w": 511,
				"h": 721
			}
		}
	],
	"meta": {
		"app": "http://www.codeandweb.com/texturepacker",
		"version": "1.0",
		"image": "spritesheet.png",
		"format": "RGBA8888",
		"size": {
			"w": 513,
			"h": 723
		},
		"scale": "1"
	}
}